skirmish/__init__.py
skirmish-0.0.1.dist-info/METADATA
skirmish-0.0.1.dist-info/WHEEL
skirmish-0.0.1.dist-info/licenses/LICENSE
skirmish-0.0.1.dist-info/RECORD
